llmlibrary/__init__.py
llmlibrary/core.py
llmlibrary-0.0.1a1.dist-info/licenses/LICENSE
llmlibrary-0.0.1a1.dist-info/METADATA
llmlibrary-0.0.1a1.dist-info/WHEEL
llmlibrary-0.0.1a1.dist-info/top_level.txt
llmlibrary-0.0.1a1.dist-info/RECORD
